oprint/__init__.py
oprint-0.1.dist-info/DESCRIPTION.rst
oprint-0.1.dist-info/METADATA
oprint-0.1.dist-info/RECORD
oprint-0.1.dist-info/WHEEL
oprint-0.1.dist-info/metadata.json
oprint-0.1.dist-info/top_level.txt
