Metadata-Version: 2.0
Name: oprint
Version: 0.1
Summary: UNKNOWN
Home-page: https://github.com/moreati/oprint
Author: Alex Willmer
Author-email: alex@moreati.org.uk
License: UNKNOWN
Keywords: pprint
Platform: ALL
Classifier: Intended Audience :: Developers
Classifier: Programming Language :: Python :: 3.6
Provides-Extra: test
Requires-Dist: pytest; extra == 'test'
